{
    "state": [
        {
            "value": 2,
            "options": []
        },
        {
            "value": 2,
            "options": []
        },
        {
            "value": 0,
            "options": [
                1,
                2
            ]
        },
        {
            "value": 2,
            "options": []
        },
        {
            "value": 0,
            "options": [
                1,
                2
            ]
        },
        {
            "value": 0,
            "options": [
                1,
                2
            ]
        },
        {
            "value": 1,
            "options": []
        },
        {
            "value": 0,
            "options": [
                1,
                2
            ]
        },
        {
            "value": 0,
            "options": [
                1,
                2
            ]
        },
        {
            "value": 0,
            "options": [
                1,
                2
            ]
        },
        {
            "value": 0,
            "options": [
                1,
                2
            ]
        },
        {
            "value": 0,
            "options": [
                1,
                2
            ]
        },
        {
            "value": 2,
            "options": []
        },
        {
            "value": 0,
            "options": [
                1,
                2
            ]
        },
        {
            "value": 0,
            "options": [
                1,
                2
            ]
        },
        {
            "value": 0,
            "options": [
                1,
                2
            ]
        },
        {
            "value": 0,
            "options": [
                1,
                2
            ]
        },
        {
            "value": 0,
            "options": [
                1,
                2
            ]
        },
        {
            "value": 1,
            "options": []
        },
        {
            "value": 0,
            "options": [
                1,
                2
            ]
        },
        {
            "value": 1,
            "options": []
        },
        {
            "value": 0,
            "options": [
                1,
                2
            ]
        },
        {
            "value": 0,
            "options": [
                1,
                2
            ]
        },
        {
            "value": 1,
            "options": []
        },
        {
            "value": 0,
            "options": [
                1,
                2
            ]
        }
    ],
    "width": 5,
    "height": 5,
    "constraints": [
        {
            "cls": "ParityConstraint",
            "parameters": {
                "idx": 17,
                "side": "both"
            }
        },
        {
            "cls": "ParityConstraint",
            "parameters": {
                "idx": 14,
                "side": "left"
            }
        },
        {
            "cls": "ParityConstraint",
            "parameters": {
                "idx": 12,
                "side": "right"
            }
        },
        {
            "cls": "ParityConstraint",
            "parameters": {
                "idx": 9,
                "side": "left"
            }
        },
        {
            "cls": "ParityConstraint",
            "parameters": {
                "idx": 0,
                "side": "right"
            }
        },
        {
            "cls": "ForbiddenMotif",
            "parameters": {
                "motif": [
                    "1",
                    "1",
                    "2"
                ]
            }
        },
        {
            "cls": "GroupSize",
            "parameters": {
                "idx": 18,
                "size": 2
            }
        }
    ]
}